pi_baseutils/__init__.py
pi_baseutils/pi_baseutils.py
pi_baseutils-0.0.6.dist-info/LICENSE
pi_baseutils-0.0.6.dist-info/METADATA
pi_baseutils-0.0.6.dist-info/WHEEL
pi_baseutils-0.0.6.dist-info/top_level.txt
pi_baseutils-0.0.6.dist-info/RECORD
