Metadata-Version: 2.1
Name: pi-baseutils
Version: 0.0.6
Summary: utils
Author-email: rhl1713 <Leeruohua@126.com>
License: MIT License
Classifier: Programming Language :: Python :: 3
Classifier: License :: OSI Approved :: MIT License
Classifier: Operating System :: OS Independent
Requires-Python: >=3.6
License-File: LICENSE
